ikamand/__init__.py
ikamand/const.py
ikamand/ikamand.py
ikamand-0.1.9.dist-info/LICENSE
ikamand-0.1.9.dist-info/METADATA
ikamand-0.1.9.dist-info/WHEEL
ikamand-0.1.9.dist-info/top_level.txt
ikamand-0.1.9.dist-info/RECORD
