Metadata-Version: 2.1
Name: ikamand
Version: 0.1.9
Home-page: https://github.com/slinkymanbyday/ikamand
Author: slinkymanbyday
Author-email: slinkymanbyday@gmail.com
Classifier: Programming Language :: Python :: 3
Classifier: License :: OSI Approved :: MIT License
Classifier: Operating System :: OS Independent
License-File: LICENSE
Requires-Dist: requests
